{"config": {"view": {"continuousWidth": 400, "continuousHeight": 300}}, "data": {"name": "data-494f34bd3e1a3b4a97b3d9822fe72397"}, "mark": "bar", "encoding": {"tooltip": [{"field": "invest", "title": "ISW Priority Community Area", "type": "nominal"}, {"field": "%_PublicSubsidy", "title": "TIF Funding to Total Project Cost per Project (Median)", "type": "quantitative"}], "x": {"field": "invest", "title": "ISW Priority Community Area", "type": "nominal"}, "y": {"field": "%_PublicSubsidy", "title": "Percentage of Total Project Cost sourced from TIF", "type": "quantitative"}}, "selection": {"selector022": {"type": "interval", "bind": "scales", "encodings": ["x", "y"]}}, "width": 400, "$schema": "https://vega.github.io/schema/vega-lite/v4.17.0.json", "datasets": {"data-494f34bd3e1a3b4a97b3d9822fe72397": [{"invest": false, "%_PublicSubsidy": 0.3634684453612792}, {"invest": true, "%_PublicSubsidy": 0.2497456189937818}]}}